Metadata-Version: 2.1
Name: topsis-ashikothari10
Version: 0.0.1
Summary: A small data preprocessing package
Home-page: https://github.com/pypa/sampleproject
Author:  Author: Ashi Kothari
Author-email: ashikothari10@gmail.com
License: UNKNOWN
Platform: UNKNOWN
Classifier: Programming Language :: Python :: 3
Classifier: License :: OSI Approved :: MIT License
Classifier: Operating System :: OS Independent
Requires-Python: >=3.6
